tests/__init__.py
tests/test_data_utils.py
tests/test_models/__init__.py
tests/test_models/test_deeprec.py
tests/test_models/test_deepsense.py
tests/test_models/test_lstnet.py
tsnn/__init__.py
tsnn/data_utils.py
tsnn/models/__init__.py
tsnn/models/deeprec.py
tsnn/models/deepsense.py
tsnn/models/lstnet.py
tsnn-0.1.3.dist-info/DESCRIPTION.rst
tsnn-0.1.3.dist-info/METADATA
tsnn-0.1.3.dist-info/RECORD
tsnn-0.1.3.dist-info/WHEEL
tsnn-0.1.3.dist-info/metadata.json
tsnn-0.1.3.dist-info/top_level.txt
