Metadata-Version: 2.0
Name: tsnn
Version: 0.1.3
Summary: Time Series Neural Networks (Keras wrapper)
Home-page: https://github.com/sofienealouini/tsnn
Author: Sofiene Alouini
Author-email: sofiene.alouini@gmail.com
License: UNKNOWN
Platform: UNKNOWN
Classifier: Programming Language :: Python :: 3
Classifier: License :: Free for non-commercial use
Classifier: Operating System :: OS Independent
Classifier: Development Status :: 1 - Planning
Classifier: Intended Audience :: Science/Research
Classifier: Topic :: Scientific/Engineering :: Artificial Intelligence
Requires-Dist: numpy (>=1.13.0)
Requires-Dist: matplotlib (>=2.1.0)
Requires-Dist: pandas (>=0.20.0)
Requires-Dist: scikit-learn (>=0.19.0)
Requires-Dist: tensorflow (>=1.3.0)
Requires-Dist: keras (>=2.0.8)
